ballpool/__init__.py
ballpool/mol.py
ballpool/real_gas.py
ballpool/vector2d.py
ballpool-0.0.0.dist-info/METADATA
ballpool-0.0.0.dist-info/WHEEL
ballpool-0.0.0.dist-info/RECORD
