Metadata-Version: 2.3
Name: ballpool
Version: 0.0.0
Summary: Particle Simulator Software
Requires-Python: >=3.10
Requires-Dist: opencv-python
Requires-Dist: pillow
